anonymous_permissions
